corautil/__init__.py
corautil/corautil.py
corautil/device_settings.py
corautil/errors.py
corautil/lgrnet_settings.py
corautil/utils.py
corautil/tests/__init__.py
corautil/tests/test_device_settings.py
corautil/tests/test_file.py
corautil/tests/test_utils.py
corautil-1.0.2.dist-info/LICENSE
corautil-1.0.2.dist-info/METADATA
corautil-1.0.2.dist-info/WHEEL
corautil-1.0.2.dist-info/top_level.txt
corautil-1.0.2.dist-info/RECORD
